{
    "configurations": [
        {
            "name": "macOS",
            "includePath": [
                "${workspaceFolder}/include",
                "${workspaceFolder}/src",
                "/Library/Developer/CommandLineTools/usr/include",
                "/Applications/Xcode.app/Contents/Developer/Platforms/MacOSX.platform/Developer/SDKs/MacOSX.sdk/System/Library/Frameworks/Metal.framework/Headers",
                "/Applications/Xcode.app/Contents/Developer/Platforms/MacOSX.platform/Developer/SDKs/MacOSX.sdk/System/Library/Frameworks/Network.framework/Headers",
                "/usr/local/lib",
                "/usr/local/include",
                "/opt/homebrew/opt",
                "/opt/homebrew/include"
            ],
            "macFrameworkPath": [
                "/System/Library/Frameworks",
                "/Library/Frameworks"
            ],
            "compilerPath": "/usr/bin/clang++",
            "cStandard": "c17",
            "cppStandard": "c++20",
            "intelliSenseMode": "macos-clang-x64"
        },
        {
            "name": "macos",
            "includePath": [
                "${default}"
            ],
            "defines": []
        }
    ],
    "version": 4
}